vers_models/Language.py
vers_models/__about__.py
vers_models/__init__.py
vers_models/cli.py
vers_models/eval.py
vers_models/main.py
vers_models/train.py
vers_models/models/BaseModel.py
vers_models/models/S2SMultiHeadAttn.py
vers_models/models/S2SNoAttn.py
vers_models/models/Transfo.py
vers_models/models/__init__.py
vers_models-0.1.2.dist-info/METADATA
vers_models-0.1.2.dist-info/WHEEL
vers_models-0.1.2.dist-info/entry_points.txt
vers_models-0.1.2.dist-info/licenses/LICENSE.txt
vers_models-0.1.2.dist-info/RECORD
