Metadata-Version: 2.4
Name: vers-models
Version: 0.1.2
Project-URL: Documentation, https://github.com/Marceau-H/vers_models#readme
Project-URL: Issues, https://github.com/Marceau-H/vers_models/issues
Project-URL: Source, https://github.com/Marceau-H/vers_models
Author-email: Marceau <pypi@marceau-h.fr>
License-Expression: AGPL-3.0-or-later
License-File: LICENSE.txt
Classifier: Development Status :: 4 - Beta
Classifier: Programming Language :: Python
Classifier: Programming Language :: Python :: 3.8
Classifier: Programming Language :: Python :: 3.9
Classifier: Programming Language :: Python :: 3.10
Classifier: Programming Language :: Python :: 3.11
Classifier: Programming Language :: Python :: 3.12
Classifier: Programming Language :: Python :: Implementation :: CPython
Classifier: Programming Language :: Python :: Implementation :: PyPy
Requires-Python: >=3.9
Requires-Dist: jiwer
Requires-Dist: numpy
Requires-Dist: scikit-learn
Requires-Dist: torch>=2.0.0
Requires-Dist: tqdm
